conways_game_of_life/__init__.py
conways_game_of_life/cli.py
conways_game_of_life/game_of_life.py
cellular_automata_game_of_life-1.0.3.dist-info/LICENSE
cellular_automata_game_of_life-1.0.3.dist-info/METADATA
cellular_automata_game_of_life-1.0.3.dist-info/WHEEL
cellular_automata_game_of_life-1.0.3.dist-info/entry_points.txt
cellular_automata_game_of_life-1.0.3.dist-info/top_level.txt
cellular_automata_game_of_life-1.0.3.dist-info/RECORD
