Metadata-Version: 2.1
Name: cellular-automata-game-of-life
Version: 1.0.3
Summary: A modern implementation of Conway's Game of Life with interactive features.
Home-page: https://github.com/shiv3679/Cellular-Automata
Author: Shiv Shankar Singh
Author-email: shivshankarsingh.py@gmail.com
License: MIT
Classifier: Programming Language :: Python :: 3
Classifier: License :: OSI Approved :: MIT License
Classifier: Operating System :: OS Independent
Requires-Python: >=3.6
License-File: LICENSE
Requires-Dist: numpy
Requires-Dist: matplotlib
